[
  {
    "data": "2025-01-01",
    "feriado": "Ano Novo (2025)"
  },
  {
    "data": "2025-03-03",
    "feriado": "Carnaval"
  },
  {
    "data": "2025-03-04",
    "feriado": "Carnaval"
  },
  {
    "data": "2025-04-18",
    "feriado": "Sexta-feira Santa (feriado nacional)"
  },
  {
    "data": "2025-04-21",
    "feriado": "Tiradentes (feriado nacional)"
  },
  {
    "data": "2025-05-01",
    "feriado": "Dia do Trabalhador (feriado nacional)"
  },
  {
    "data": "2025-09-07",
    "feriado": "Independência do Brasil (feriado nacional)"
  },
  {
    "data": "2025-10-12",
    "feriado": "Nossa Sra. Aparecida (feriado nacional)"
  },
  {
    "data": "2025-11-02",
    "feriado": "Finados (feriado nacional)"
  },
  {
    "data": "2025-11-15",
    "feriado": "Proclamação da República (feriado nacional)"
  },
  {
    "data": "2025-11-20",
    "feriado": "Dia da Consciência Negra (feriado nacional)"
  },
  {
    "data": "2025-12-25",
    "feriado": "Natal (feriado nacional)"
  },
  {
    "data": "2026-01-01",
    "feriado": "Ano Novo (2026)"
  }
]
